Verilog/Assignment_1/q5/a5.v
module my1BLshifter (input A, input B, input C, input D, output a, output b, output c, output d);
    buf(a, B);
    buf(b, C);
    buf(c, D);
    buf(d, A);
endmodule

module my1BRshifter (input A, input B, input C, input D, output e, output f, output g, output h);
    buf(e, D);
    buf(f, A);
    buf(g, B);
    buf(h, C);
endmodule

module my2BLshifter (input A, input B, input C, input D, output i, output j, output k, output l);
    buf(i, C);
    buf(j, D);
    buf(k, A);
    buf(l, B);
endmodule

module my2BRshifter (input A, input B, input C, input D, output m, output n, output o, output p);
    buf(m, C);
    buf(n, D);
    buf(o, A);
    buf(p, B);
endmodule

module a5_tb();
    reg A,B,C,D;
    wire a, b, c, d, e, f, g, h, i, j, k, l, m, n, o, p;

    my1BLshifter BS1 (A, B, C, D, a, b, c, d);
    my1BRshifter BS2 (A, B, C, D, e, f, g, h);
    my2BLshifter BS3 (A, B, C, D, i, j, k, l);
    my2BRshifter BS4 (A, B, C, D, m, n, o, p);

    initial begin
        $dumpfile("a5_tb.vcd");
        $dumpvars(0, a5_tb);

        A=0; B=0; C=0; D=0; #10;
        A=0; B=0; C=0; D=1; #10;
        A=0; B=0; C=1; D=0; #10;
        A=0; B=0; C=1; D=1; #10;
    
        A=0; B=1; C=0; D=0; #10;
        A=0; B=1; C=0; D=1; #10;
        A=0; B=1; C=1; D=0; #10;
        A=0; B=1; C=1; D=1; #10;
    
        A=1; B=0; C=0; D=0; #10;
        A=1; B=0; C=0; D=1; #10;
        A=1; B=0; C=1; D=0; #10;
        A=1; B=0; C=1; D=1; #10;
    
        A=1; B=1; C=0; D=0; #10;
        A=1; B=1; C=0; D=1; #10;
        A=1; B=1; C=1; D=0; #10;
        A=1; B=1; C=1; D=1; #10;

    end
endmodule

Verilog/Assignment_1/q5/a5_tb.vcd
$date
	Mon Sep 08 17:25:42 2025
$end
$version
	Icarus Verilog
$end
$timescale
	1s
$end
$scope module a5_tb $end
$var wire 1 ! p $end
$var wire 1 " o $end
$var wire 1 # n $end
$var wire 1 $ m $end
$var wire 1 % l $end
$var wire 1 & k $end
$var wire 1 ' j $end
$var wire 1 ( i $end
$var wire 1 ) h $end
$var wire 1 * g $end
$var wire 1 + f $end
$var wire 1 , e $end
$var wire 1 - d $end
$var wire 1 . c $end
$var wire 1 / b $end
$var wire 1 0 a $end
$var reg 1 1 A $end
$var reg 1 2 B $end
$var reg 1 3 C $end
$var reg 1 4 D $end
$scope module BS1 $end
$var wire 1 1 A $end
$var wire 1 2 B $end
$var wire 1 3 C $end
$var wire 1 4 D $end
$var wire 1 0 a $end
$var wire 1 / b $end
$var wire 1 . c $end
$var wire 1 - d $end
$upscope $end
$scope module BS2 $end
$var wire 1 1 A $end
$var wire 1 2 B $end
$var wire 1 3 C $end
$var wire 1 4 D $end
$var wire 1 , e $end
$var wire 1 + f $end
$var wire 1 * g $end
$var wire 1 ) h $end
$upscope $end
$scope module BS3 $end
$var wire 1 1 A $end
$var wire 1 2 B $end
$var wire 1 3 C $end
$var wire 1 4 D $end
$var wire 1 ( i $end
$var wire 1 ' j $end
$var wire 1 & k $end
$var wire 1 % l $end
$upscope $end
$scope module BS4 $end
$var wire 1 1 A $end
$var wire 1 2 B $end
$var wire 1 3 C $end
$var wire 1 4 D $end
$var wire 1 $ m $end
$var wire 1 # n $end
$var wire 1 " o $end
$var wire 1 ! p $end
$upscope $end
$upscope $end
$enddefinitions $end
$comment Show the parameter values. $end
$dumpall
$end
#0
$dumpvars
04
03
02
01
00
0/
0.
0-
0,
0+
0*
0)
0(
0'
0&
0%
0$
0#
0"
0!
$end
#10
1.
1,
1'
1#
14
#20
0.
0,
0'
0#
1/
1)
1(
1$
04
13
#30
1.
1,
1'
1#
14
#40
0.
0,
0'
0#
0/
0)
0(
0$
10
1*
1%
1!
04
03
12
#50
1.
1,
1'
1#
14
#60
0.
0,
0'
0#
1/
1)
1(
1$
04
13
#70
1.
1,
1'
1#
14
#80
0.
0,
0'
0#
0/
0)
0(
0$
00
0*
0%
0!
1-
1+
1&
1"
04
03
02
11
#90
1.
1,
1'
1#
14
#100
0.
0,
0'
0#
1/
1)
1(
1$
04
13
#110
1.
1,
1'
1#
14
#120
0.
0,
0'
0#
0/
0)
0(
0$
10
1*
1%
1!
04
03
12
#130
1.
1,
1'
1#
14
#140
0.
0,
0'
0#
1/
1)
1(
1$
04
13
#150
1.
1,
1'
1#
14
