Verilog/Assignment_1/q6/a6.v
module mymux2to1 (input a, input b, input s, output y);
    wire w1, w2, s;
    not(ns, s);
    and(w1, a, ns);
    and(w2, b, s);
    or(y, w1, w2);
endmodule

module mymux4to1 (input a, input b, input c, input d, input s, input t, output y);
    wire w1, w2;
    mymux2to1 M1 (.a(a), .b(b), .s(t), .y(w1));
    mymux2to1 M2 (.a(c), .b(d), .s(t), .y(w2));
    mymux2to1 M3 (.a(w1), .b(w2), .s(s), .y(y));
endmodule

module mymux8to1 (input a, input b, input c, input d, input e, input f, input g, input h, input [2:0] s, output y);
    wire w1, w2;
    mymux4to1 M1 (.a(a), .b(b), .c(c), .d(d), .s(s[1]), .t(s[0]), .y(w1));
    mymux4to1 M2 (.a(e), .b(f), .c(g), .d(h), .s(s[1]), .t(s[0]), .y(w2));
    mymux2to1 M3 (.a(w1), .b(w2), .s(s[2]), .y(y));
endmodule    

module myhalfadder (input a, input b, output sum, output carry);
    xor(sum, a, b);
    and(carry, a, b);
endmodule

module myhalfsubtractor (input a, input b, output diff, output borrow);
    wire na;
    not (na, a);
    xor(diff, a, b);
    and(borrow, na, b);
endmodule

module mymultiplier (input a, input b, output c);
    and(c, a, b);
endmodule


module myALU (input a, input b, input [2:0] OC, output o1, output o2);
    wire y1_sum, y1_carry, y2_diff, y2_borrow, y3, y4, y5, y6;
    myhalfadder addition (.a(a), .b(b), .sum(y1_sum), .carry(y1_carry));
    myhalfsubtractor subtraction (.a(a), .b(b), .diff(y2_diff), .borrow(y2_borrow));
    mymultiplier multiplication (.a(a), .b(b), .c(y3));
    or(y4, a, b);
    and(y5, a, b);
    xor(y6, a, b);

    mymux8to1 MUX1 (.a(y1_sum), .b(y2_diff), .c(y3), .d(y4), .e(y5), .f(y6), .g(1'bz), .h(1'bz), .s(OC), .y(o1));
    mymux8to1 MUX2 (.a(y1_carry), .b(y2_borrow), .c(1'bz), .d(1'bz), .e(1'bz), .f(1'bz), .g(1'bz), .h(1'bz), .s(OC), .y(o2)); 
endmodule

module a6_tb();

    reg a, b;
    reg [2:0] OC;
    wire o1, o2;

    myALU ALU (a, b, OC, o1, o2);

    initial begin
        $dumpfile("a6_tb.vcd");
        $dumpvars(0,a6_tb);

        a = 1; b = 1; OC = 3'b000; #10;
        a = 1; b = 0; OC = 3'b001; #10;
        a = 0; b = 1; OC = 3'b010; #10;
        a = 0; b = 1; OC = 3'b011; #10;
        a = 1; b = 0; OC = 3'b100; #10;
        a = 1; b = 0; OC = 3'b101; #10;
        a = 1; b = 1; OC = 3'b110; #10;
        a = 1; b = 1; OC = 3'b111; #10;
    end

endmodule

Verilog/Assignment_1/q6/a6_tb.vcd
$date
	Mon Sep 08 17:32:39 2025
$end
$version
	Icarus Verilog
$end
$timescale
	1s
$end
$scope module a6_tb $end
$var wire 1 ! o2 $end
$var wire 1 " o1 $end
$var reg 3 # OC [2:0] $end
$var reg 1 $ a $end
$var reg 1 % b $end
$scope module ALU $end
$var wire 3 & OC [2:0] $end
$var wire 1 $ a $end
$var wire 1 % b $end
$var wire 1 ' y4 $end
$var wire 1 ( y5 $end
$var wire 1 ) y6 $end
$var wire 1 * y3 $end
$var wire 1 + y2_diff $end
$var wire 1 , y2_borrow $end
$var wire 1 - y1_sum $end
$var wire 1 . y1_carry $end
$var wire 1 ! o2 $end
$var wire 1 " o1 $end
$scope module MUX1 $end
$var wire 1 ' d $end
$var wire 1 ( e $end
$var wire 1 ) f $end
$var wire 1 / g $end
$var wire 1 0 h $end
$var wire 3 1 s [2:0] $end
$var wire 1 " y $end
$var wire 1 2 w2 $end
$var wire 1 3 w1 $end
$var wire 1 * c $end
$var wire 1 + b $end
$var wire 1 - a $end
$scope module M1 $end
$var wire 1 ' d $end
$var wire 1 4 s $end
$var wire 1 5 t $end
$var wire 1 3 y $end
$var wire 1 6 w2 $end
$var wire 1 7 w1 $end
$var wire 1 * c $end
$var wire 1 + b $end
$var wire 1 - a $end
$scope module M1 $end
$var wire 1 8 ns $end
$var wire 1 5 s $end
$var wire 1 9 w1 $end
$var wire 1 : w2 $end
$var wire 1 7 y $end
$var wire 1 + b $end
$var wire 1 - a $end
$upscope $end
$scope module M2 $end
$var wire 1 ' b $end
$var wire 1 ; ns $end
$var wire 1 5 s $end
$var wire 1 < w1 $end
$var wire 1 = w2 $end
$var wire 1 6 y $end
$var wire 1 * a $end
$upscope $end
$scope module M3 $end
$var wire 1 7 a $end
$var wire 1 6 b $end
$var wire 1 > ns $end
$var wire 1 4 s $end
$var wire 1 ? w1 $end
$var wire 1 @ w2 $end
$var wire 1 3 y $end
$upscope $end
$upscope $end
$scope module M2 $end
$var wire 1 ( a $end
$var wire 1 ) b $end
$var wire 1 / c $end
$var wire 1 0 d $end
$var wire 1 A s $end
$var wire 1 B t $end
$var wire 1 2 y $end
$var wire 1 C w2 $end
$var wire 1 D w1 $end
$scope module M1 $end
$var wire 1 ( a $end
$var wire 1 ) b $end
$var wire 1 E ns $end
$var wire 1 B s $end
$var wire 1 F w1 $end
$var wire 1 G w2 $end
$var wire 1 D y $end
$upscope $end
$scope module M2 $end
$var wire 1 / a $end
$var wire 1 0 b $end
$var wire 1 H ns $end
$var wire 1 B s $end
$var wire 1 I w1 $end
$var wire 1 J w2 $end
$var wire 1 C y $end
$upscope $end
$scope module M3 $end
$var wire 1 D a $end
$var wire 1 C b $end
$var wire 1 K ns $end
$var wire 1 A s $end
$var wire 1 L w1 $end
$var wire 1 M w2 $end
$var wire 1 2 y $end
$upscope $end
$upscope $end
$scope module M3 $end
$var wire 1 3 a $end
$var wire 1 2 b $end
$var wire 1 N ns $end
$var wire 1 O s $end
$var wire 1 P w1 $end
$var wire 1 Q w2 $end
$var wire 1 " y $end
$upscope $end
$upscope $end
$scope module MUX2 $end
$var wire 1 R c $end
$var wire 1 S d $end
$var wire 1 T e $end
$var wire 1 U f $end
$var wire 1 V g $end
$var wire 1 W h $end
$var wire 3 X s [2:0] $end
$var wire 1 ! y $end
$var wire 1 Y w2 $end
$var wire 1 Z w1 $end
$var wire 1 , b $end
$var wire 1 . a $end
$scope module M1 $end
$var wire 1 R c $end
$var wire 1 S d $end
$var wire 1 [ s $end
$var wire 1 \ t $end
$var wire 1 Z y $end
$var wire 1 ] w2 $end
$var wire 1 ^ w1 $end
$var wire 1 , b $end
$var wire 1 . a $end
$scope module M1 $end
$var wire 1 _ ns $end
$var wire 1 \ s $end
$var wire 1 ` w1 $end
$var wire 1 a w2 $end
$var wire 1 ^ y $end
$var wire 1 , b $end
$var wire 1 . a $end
$upscope $end
$scope module M2 $end
$var wire 1 R a $end
$var wire 1 S b $end
$var wire 1 b ns $end
$var wire 1 \ s $end
$var wire 1 c w1 $end
$var wire 1 d w2 $end
$var wire 1 ] y $end
$upscope $end
$scope module M3 $end
$var wire 1 ^ a $end
$var wire 1 ] b $end
$var wire 1 e ns $end
$var wire 1 [ s $end
$var wire 1 f w1 $end
$var wire 1 g w2 $end
$var wire 1 Z y $end
$upscope $end
$upscope $end
$scope module M2 $end
$var wire 1 T a $end
$var wire 1 U b $end
$var wire 1 V c $end
$var wire 1 W d $end
$var wire 1 h s $end
$var wire 1 i t $end
$var wire 1 Y y $end
$var wire 1 j w2 $end
$var wire 1 k w1 $end
$scope module M1 $end
$var wire 1 T a $end
$var wire 1 U b $end
$var wire 1 l ns $end
$var wire 1 i s $end
$var wire 1 m w1 $end
$var wire 1 n w2 $end
$var wire 1 k y $end
$upscope $end
$scope module M2 $end
$var wire 1 V a $end
$var wire 1 W b $end
$var wire 1 o ns $end
$var wire 1 i s $end
$var wire 1 p w1 $end
$var wire 1 q w2 $end
$var wire 1 j y $end
$upscope $end
$scope module M3 $end
$var wire 1 k a $end
$var wire 1 j b $end
$var wire 1 r ns $end
$var wire 1 h s $end
$var wire 1 s w1 $end
$var wire 1 t w2 $end
$var wire 1 Y y $end
$upscope $end
$upscope $end
$scope module M3 $end
$var wire 1 Z a $end
$var wire 1 Y b $end
$var wire 1 u ns $end
$var wire 1 v s $end
$var wire 1 w w1 $end
$var wire 1 x w2 $end
$var wire 1 ! y $end
$upscope $end
$upscope $end
$scope module addition $end
$var wire 1 $ a $end
$var wire 1 % b $end
$var wire 1 . carry $end
$var wire 1 - sum $end
$upscope $end
$scope module multiplication $end
$var wire 1 $ a $end
$var wire 1 % b $end
$var wire 1 * c $end
$upscope $end
$scope module subtraction $end
$var wire 1 $ a $end
$var wire 1 % b $end
$var wire 1 , borrow $end
$var wire 1 + diff $end
$var wire 1 y na $end
$upscope $end
$upscope $end
$upscope $end
$enddefinitions $end
$comment Show the parameter values. $end
$dumpall
$end
#0
$dumpvars
0y
0x
1w
0v
1u
0t
xs
1r
0q
xp
1o
0n
xm
1l
xk
xj
0i
0h
0g
1f
1e
0d
xc
1b
0a
1`
1_
1^
x]
0\
0[
1Z
xY
b0 X
zW
zV
zU
zT
zS
zR
0Q
0P
0O
1N
0M
1L
1K
0J
xI
1H
0G
1F
1E
1D
xC
0B
0A
0@
0?
1>
0=
1<
1;
0:
09
18
07
16
05
04
03
12
b0 1
z0
z/
1.
0-
0,
0+
1*
0)
1(
1'
b0 &
1%
1$
b0 #
0"
1!
$end
#10
0!
1"
0w
1P
0Z
13
0f
1?
0I
0c
0m
0p
0^
17
08
0;
1=
0E
0H
xJ
0_
0b
xd
0l
xn
0o
xq
0F
1G
09
0`
0<
1:
15
1B
1\
1i
0(
1)
1-
0.
0*
1+
b1 #
b1 &
b1 1
b1 X
0%
#20
0"
0P
x!
03
x2
xw
xY
0?
19
17
06
0L
0D
xI
xC
xZ
xc
x]
0s
xm
xk
xp
xj
0>
0@
18
0:
1;
0=
0K
xM
1E
0G
1H
0J
0e
xg
1_
1b
0d
0r
xt
1l
0n
1o
0q
14
05
1A
0B
1[
0\
1h
0i
1,
1y
b10 #
b10 &
b10 1
b10 X
1%
0$
#30
1"
1P
13
1@
09
16
1D
0I
1^
0c
0m
0p
08
1:
0;
1=
0E
1G
0H
xJ
0_
1a
0b
xd
0l
xn
0o
xq
15
1B
1\
1i
b11 #
b11 &
b11 1
b11 X
#40
1?
x!
xs
0"
13
19
17
06
02
0D
xI
xC
0P
0Z
xc
x]
xY
xm
xk
xp
xj
0w
0^
1>
0@
18
0:
1;
0=
1K
0M
1E
0G
1H
0J
0N
0Q
1e
0g
1_
1b
0d
1r
0t
1l
0n
1o
0q
0u
xx
0a
04
05
0A
0B
1O
0[
0\
0h
0i
1v
0,
0y
b100 #
b100 &
b100 1
b100 X
0%
1$
#50
1"
1Q
12
1L
09
16
1D
0I
0c
0m
0p
08
1:
0;
1=
0E
1G
0H
xJ
0_
0b
xd
0l
xn
0o
xq
15
1B
1\
1i
b101 #
b101 &
b101 1
b101 X
#60
x"
x!
xQ
xx
13
x2
1^
xY
0?
1<
16
0L
1F
xI
xC
xZ
1`
xc
x]
0s
xm
xk
xp
xj
1D
07
0>
1@
18
1;
0=
0K
xM
1E
1H
0J
0e
xg
1_
1b
0d
0r
xt
1l
0n
1o
0q
0G
0:
14
05
1A
0B
1[
0\
1h
0i
1(
0)
0-
1.
1*
0+
b110 #
b110 &
b110 1
b110 X
1%
#70
0D
0^
0<
0F
0I
0`
0c
0m
0p
08
0;
1=
0E
0H
xJ
0_
0b
xd
0l
xn
0o
xq
15
1B
1\
1i
b111 #
b111 &
b111 1
b111 X
