Verilog/Assignment_3/q1/a1.v

module srlatch_are (input AE, AR, S, R, output reg Q);
    initial Q = 1'b0;
    always @(AR, AE, S, R)
        begin
            if (AR) Q <= 0;
            else 
                begin
                    if (AE == 1)
                        begin
                            if (S == 0 & R == 0) Q <= 1'bx;
                            else if (S == 0 & R == 1) Q <= 0;
                            else if (S == 1 & R == 0) Q <= 1;
                        end
                end
        end
endmodule

module a1_tb();
    reg AE, AR, S, R;
    wire Q;

    srlatch_are SR (.AE(AE), .AR(AR), .S(S), .R(R), .Q(Q));

    initial begin
        $dumpfile("a1_tb.vcd");
        $dumpvars(0,a1_tb);
        
        AR = 1; AE = 0; S = 1; R = 1; #10;
        AR = 1; AE = 1; S = 0; R = 1; #10;
        AR = 1; AE = 1; S = 1; R = 1; #10;
        AR = 0; AE = 0; S = 0; R = 1; #10;
        AR = 0; AE = 0; S = 1; R = 0; #10;
        AR = 0; AE = 0; S = 1; R = 1; #10;
        AR = 0; AE = 1; S = 0; R = 0; #10;
        AR = 0; AE = 1; S = 0; R = 1; #10;
        AR = 0; AE = 1; S = 1; R = 0; #10;
        AR = 0; AE = 1; S = 1; R = 1; #10;
        
        $finish;
    end

endmodule

Verilog/Assignment_3/q1/a1_tb.vcd
$date
	Fri Sep 19 08:19:22 2025
$end
$version
	Icarus Verilog
$end
$timescale
	1s
$end
$scope module a1_tb $end
$var wire 1 ! Q $end
$var reg 1 " AE $end
$var reg 1 # AR $end
$var reg 1 $ R $end
$var reg 1 % S $end
$scope module SR $end
$var wire 1 " AE $end
$var wire 1 # AR $end
$var wire 1 $ R $end
$var wire 1 % S $end
$var reg 1 ! Q $end
$upscope $end
$upscope $end
$enddefinitions $end
$comment Show the parameter values. $end
$dumpall
$end
#0
$dumpvars
1%
1$
1#
0"
0!
$end
#10
0%
1"
#20
1%
#30
0%
0"
0#
#40
0$
1%
#50
1$
#60
x!
0$
0%
1"
#70
0!
1$
#80
1!
0$
1%
#90
1$
