Verilog/Assignment_2/q6/a6.v
module myhalfadder (input a, input b, output reg sum, output reg carry);
    always @(*) begin
        sum   = a ^ b;
        carry = a & b;
    end
endmodule

module myfulladder (input  a, input  b, input  cin, output reg sum, output reg carry);
    always @(*) begin
        sum   = a ^ b ^ cin;
        carry = (a & b) | (b & cin) | (a & cin);
    end
endmodule

module myWTM4bit (input [3:0] a, input [3:0] b, output [7:0] o);
    wire [15:0] w;
    wire s1, s2, s3, s4, s5, s6, s7, s8, s9, s10, s11, s12;
    wire c1, c2, c3, c4, c5, c6, c7, c8, c9, c10, c11, c12;

    assign w[0] = a[0] & b[0]; 
    assign w[1] = a[1] & b[0];
    assign w[2] = a[0] & b[1];
    assign w[3] = a[2] & b[0];
    assign w[4] = a[1] & b[1];
    assign w[5] = a[0] & b[2];
    assign w[6] = a[3] & b[0];
    assign w[7] = a[2] & b[1];
    assign w[8] = a[1] & b[2];
    assign w[9] = a[0] & b[3];
    assign w[10] = a[3] & b[1];
    assign w[11] = a[2] & b[2];
    assign w[12] = a[1] & b[3];
    assign w[13] = a[3] & b[2];
    assign w[14] = a[2] & b[3];
    assign w[15] = a[3] & b[3];

    myhalfadder HA1 (.a(w[6]), .b(w[7]), .sum(s1), .carry(c1));
    myhalfadder HA2 (.a(w[10]), .b(w[11]), .sum(s2), .carry(c2));
    myfulladder FA4 (.a(w[8]), .b(w[9]), .cin(s1), .sum(s4), .carry(c4));
    myfulladder FA5 (.a(s2), .b(c1), .cin(w[12]), .sum(s5), .carry(c5));
    myfulladder FA6 (.a(w[13]), .b(w[14]), .cin(c2), .sum(s6), .carry(c6));


    myhalfadder HA3 (.a(w[3]), .b(w[4]), .sum(s3), .carry(c3));
    myhalfadder HA7 (.a(w[1]), .b(w[2]), .sum(s7), .carry(c7)); 
    myfulladder FA8 (.a(s3), .b(c7), .cin(w[5]), .sum(s8), .carry(c8)); 
    myfulladder FA9 (.a(c3), .b(s4), .cin(c8), .sum(s9), .carry(c9)); 
    myfulladder FA10 (.a(c9), .b(s5), .cin(c4), .sum(s10), .carry(c10)); 
    myfulladder FA11 (.a(c10), .b(s6), .cin(c5), .sum(s11), .carry(c11)); 
    myfulladder FA12 (.a(c6), .b(c11), .cin(w[15]), .sum(s12), .carry(c12)); 

    assign o[0] = w[0];
    assign o[1] = s7;
    assign o[2] = s8;
    assign o[3] = s9;
    assign o[4] = s10;
    assign o[5] = s11;
    assign o[6] = s12;
    assign o[7] = c12;
endmodule

module a6_tb();
    reg [3:0] a, b;
    wire [7:0] o;

    myWTM4bit w (
        .a(a),
        .b(b),
        .o(o)
    );

    initial begin
        $dumpfile("a6_tb.vcd");
        $dumpvars(0, a6_tb);
        a = 4'b1001; b = 4'b0110; #10;  
        a = 4'b1111; b = 4'b1111; #10;  
        a = 4'b0111; b = 4'b0011; #10;  
        a = 4'b1100; b = 4'b0101; #10;  
        a = 4'b0001; b = 4'b1111; #10;
        a = 4'b1110; b = 4'b0001; #10;
        a = 4'b1010; b = 4'b0101; #10;
        a = 4'b1000; b = 4'b1000; #10;
        a = 4'b0110; b = 4'b0110; #10;
        a = 4'b1111; b = 4'b0000; #10;
        
    end
endmodule

Verilog/Assignment_2/q6/a6_tb.vcd
$date
	Wed Sep 10 22:14:52 2025
$end
$version
	Icarus Verilog
$end
$timescale
	1s
$end
$scope module a6_tb $end
$var wire 8 ! o [7:0] $end
$var reg 4 " a [3:0] $end
$var reg 4 # b [3:0] $end
$scope module w $end
$var wire 4 $ a [3:0] $end
$var wire 4 % b [3:0] $end
$var wire 16 & w [15:0] $end
$var wire 1 ' s9 $end
$var wire 1 ( s8 $end
$var wire 1 ) s7 $end
$var wire 1 * s6 $end
$var wire 1 + s5 $end
$var wire 1 , s4 $end
$var wire 1 - s3 $end
$var wire 1 . s2 $end
$var wire 1 / s12 $end
$var wire 1 0 s11 $end
$var wire 1 1 s10 $end
$var wire 1 2 s1 $end
$var wire 8 3 o [7:0] $end
$var wire 1 4 c9 $end
$var wire 1 5 c8 $end
$var wire 1 6 c7 $end
$var wire 1 7 c6 $end
$var wire 1 8 c5 $end
$var wire 1 9 c4 $end
$var wire 1 : c3 $end
$var wire 1 ; c2 $end
$var wire 1 < c12 $end
$var wire 1 = c11 $end
$var wire 1 > c10 $end
$var wire 1 ? c1 $end
$scope module FA10 $end
$var wire 1 9 cin $end
$var wire 1 + b $end
$var wire 1 4 a $end
$var reg 1 > carry $end
$var reg 1 1 sum $end
$upscope $end
$scope module FA11 $end
$var wire 1 > a $end
$var wire 1 8 cin $end
$var wire 1 * b $end
$var reg 1 = carry $end
$var reg 1 0 sum $end
$upscope $end
$scope module FA12 $end
$var wire 1 = b $end
$var wire 1 @ cin $end
$var wire 1 7 a $end
$var reg 1 < carry $end
$var reg 1 / sum $end
$upscope $end
$scope module FA4 $end
$var wire 1 A a $end
$var wire 1 B b $end
$var wire 1 2 cin $end
$var reg 1 9 carry $end
$var reg 1 , sum $end
$upscope $end
$scope module FA5 $end
$var wire 1 C cin $end
$var wire 1 ? b $end
$var wire 1 . a $end
$var reg 1 8 carry $end
$var reg 1 + sum $end
$upscope $end
$scope module FA6 $end
$var wire 1 D a $end
$var wire 1 E b $end
$var wire 1 ; cin $end
$var reg 1 7 carry $end
$var reg 1 * sum $end
$upscope $end
$scope module FA8 $end
$var wire 1 F cin $end
$var wire 1 6 b $end
$var wire 1 - a $end
$var reg 1 5 carry $end
$var reg 1 ( sum $end
$upscope $end
$scope module FA9 $end
$var wire 1 , b $end
$var wire 1 5 cin $end
$var wire 1 : a $end
$var reg 1 4 carry $end
$var reg 1 ' sum $end
$upscope $end
$scope module HA1 $end
$var wire 1 G a $end
$var wire 1 H b $end
$var reg 1 ? carry $end
$var reg 1 2 sum $end
$upscope $end
$scope module HA2 $end
$var wire 1 I a $end
$var wire 1 J b $end
$var reg 1 ; carry $end
$var reg 1 . sum $end
$upscope $end
$scope module HA3 $end
$var wire 1 K a $end
$var wire 1 L b $end
$var reg 1 : carry $end
$var reg 1 - sum $end
$upscope $end
$scope module HA7 $end
$var wire 1 M a $end
$var wire 1 N b $end
$var reg 1 6 carry $end
$var reg 1 ) sum $end
$upscope $end
$upscope $end
$upscope $end
$enddefinitions $end
$comment Show the parameter values. $end
$dumpall
$end
#0
$dumpvars
1N
0M
0L
0K
0J
1I
0H
0G
1F
0E
1D
0C
0B
0A
0@
0?
0>
0=
0<
0;
0:
09
08
07
06
05
04
b110110 3
02
11
10
0/
1.
0-
0,
1+
1*
1)
1(
0'
b10010000100100 &
b110 %
b1001 $
b110 #
b1001 "
b110110 !
$end
#10
1>
01
1/
14
1=
10
15
0(
0'
1<
16
0)
1:
1?
19
1;
0.
18
0+
17
1*
b11100001 !
b11100001 3
1G
1B
1@
1M
1K
1L
1H
1A
1J
1C
1E
b1111111111111111 &
b1111 #
b1111 %
b1111 "
b1111 $
#20
00
0>
11
0=
0*
0<
05
1(
09
1,
08
0?
12
0;
07
b10101 !
b10101 3
0/
0F
0A
0B
0J
0C
0E
0G
0I
0D
0@
b10011111 &
b11 #
b11 %
b111 "
b111 $
#30
1+
04
1'
10
1.
06
0:
1-
1*
0H
1J
b111100 !
b111100 3
0M
0N
0L
1G
1D
b10100001001000 &
b101 #
b101 %
b1100 "
b1100 $
#40
01
0+
00
1)
0-
05
1(
02
09
1,
0.
0*
b1111 !
b1111 3
1N
0K
1F
0G
1B
0J
0D
b1000100101 &
b1111 #
b1111 %
b1 "
b1 $
#50
1'
1-
1(
12
1,
b1110 !
b1110 3
1M
0N
1K
0F
1G
0B
b1001010 &
b1 #
b1 %
b1110 "
b1110 $
#60
11
0'
10
b110010 !
b110010 3
0(
19
0,
1*
0-
1A
1D
0K
b10000101000010 &
b101 #
b101 %
b1010 "
b1010 $
#70
00
01
0'
02
0*
1/
b1000000 !
b1000000 3
0)
09
0,
0G
0D
1@
0M
0A
b1000000000000000 &
b1000 #
b1000 %
b1000 "
b1000 $
#80
10
1>
1(
19
0'
1+
1-
12
0,
1.
b100100 !
b100100 3
0/
1L
1H
1A
1J
0@
b100110010000 &
b110 #
b110 %
b110 "
b110 $
#90
00
0(
0>
b0 !
b0 3
0'
0+
0-
02
09
0,
0.
0L
0H
0A
0J
b0 &
b0 #
b0 %
b1111 "
b1111 $
