Verilog/Assignment_4/q4/a4.v
module modular_2a_b_fsm (input reset, clk, a, b, output o);
	reg [1:0] state, nstate;
	parameter s0 = 4'b00;
	parameter s1 = 4'b01;
	parameter s2 = 4'b10;
	parameter s3 = 4'b11;
	
	initial state = s0;
	always @(posedge reset, posedge clk)
		if (reset) state <= s0;
		else state <= nstate;
	
	always @(*)
		nstate = state + 2 * a + b;
	
	assign o = (state == s1);	 
endmodule

module a4_tb();
	reg clk, reset, a, b;
	wire o;
	
	modular_2a_b_fsm ModularFSM (reset, clk, a, b, o);

	initial clk = 0;
	always begin
		#5;
		clk = ~clk;
	end

	initial begin
		$dumpfile("a4_tb.vcd");
		$dumpvars(0, a4_tb);


		$display("r|a|b|o");
		$display("-------");
		$monitor("%b|%b|%b|%b", reset, a, b, o);
		
		// s0
		reset = 0; a = 0; b = 1; #10; // s1    //output = 1
		reset = 0; a = 1; b = 0; #10; // s3   
		reset = 0; a = 1; b = 1; #10; // s2
		reset = 0; a = 1; b = 1; #10; // s1
		reset = 1; a = 0; b = 1; #15; // s0
		reset = 0; a = 1; b = 1; #10; // s3
		reset = 0; a = 1; b = 0; #10; // s1
		reset = 0; a = 0; b = 1; #10; // s2
		$finish;
	end
endmodule

Verilog/Assignment_4/q4/a4_tb.vcd
$date
	Thu Sep 18 22:05:16 2025
$end
$version
	Icarus Verilog
$end
$timescale
	1s
$end
$scope module a4_tb $end
$var wire 1 ! o $end
$var reg 1 " a $end
$var reg 1 # b $end
$var reg 1 $ clk $end
$var reg 1 % reset $end
$scope module ModularFSM $end
$var wire 1 " a $end
$var wire 1 # b $end
$var wire 1 $ clk $end
$var wire 1 % reset $end
$var wire 1 ! o $end
$var parameter 4 & s0 $end
$var parameter 4 ' s1 $end
$var parameter 4 ( s2 $end
$var parameter 4 ) s3 $end
$var reg 2 * nstate [1:0] $end
$var reg 2 + state [1:0] $end
$upscope $end
$upscope $end
$enddefinitions $end
$comment Show the parameter values. $end
$dumpall
b11 )
b10 (
b1 '
b0 &
$end
#0
$dumpvars
b0 +
b1 *
0%
0$
1#
0"
0!
$end
#5
b10 *
1!
b1 +
1$
#10
b11 *
0$
0#
1"
#15
b1 *
0!
b11 +
1$
#20
b10 *
0$
1#
#25
b1 *
b10 +
1$
#30
0$
#35
b0 *
1!
b1 +
1$
#40
0!
b0 +
b1 *
0$
0"
1%
#45
1$
#50
0$
#55
b11 +
b10 *
1$
1"
0%
#60
0$
#65
1!
b1 +
b11 *
1$
0#
#70
0$
#75
0!
b10 +
b11 *
1$
1#
0"
#80
0$
#85
b0 *
b11 +
1$
