Verilog/Assignment_4/q3/a3.v
module sequencematcher (input reset, clk, x, output o);
	reg [3:0] state, nstate;
	parameter s0 = 3'b000;
	parameter s1 = 3'b001;
	parameter s2 = 3'b010;
	parameter s3 = 3'b011;
	parameter s4 = 3'b100;
	
	initial state = s0;	
	always @(posedge clk, posedge reset)
		if(reset) state <= s0;
		else state <= nstate;
	
	always @(*)
		case(state)
			s0: nstate = x ? s1 : s0;
			s1: nstate = x ? s2 : s0;
			s2: nstate = ~x ? s3 : s2;
			s3: nstate = x ? s4 : s0;
			s4: nstate = s4;
			default nstate = s0;
		endcase

	assign o = (state == s4);
endmodule

module a3_tb();
	reg reset, clk, x;
	wire o;
	
	sequencematcher SM (reset, clk, x, o);	

	initial clk = 0;
	always begin
		#5;
		clk = ~clk;
	end

	initial begin
		$dumpfile("a3_tb.vcd");
		$dumpvars(0,a3_tb);

		$display("r|x|o");
		$display("-----");
		$monitor("%b|%b|%b", reset, x, o);
		
		// s0
		reset = 0; x = 0; #10; // s0
 		reset = 0; x = 1; #10; // s1
 		reset = 0; x = 1; #10; // s2
		reset = 0; x = 1; #10; // s2
		reset = 0; x = 0; #10; // s3
		reset = 0; x = 1; #10; // s4
		reset = 0; x = 1; #10; // s4
		reset = 1; x = 1; #10; // s0
		reset = 1; x = 1; #10; // s0
		reset = 0; x = 1; #10; // s1
	 

		$finish;

	end
endmodule

Verilog/Assignment_4/q3/a3_tb.vcd
$date
	Thu Sep 18 22:14:06 2025
$end
$version
	Icarus Verilog
$end
$timescale
	1s
$end
$scope module a3_tb $end
$var wire 1 ! o $end
$var reg 1 " clk $end
$var reg 1 # reset $end
$var reg 1 $ x $end
$scope module SM $end
$var wire 1 " clk $end
$var wire 1 # reset $end
$var wire 1 $ x $end
$var wire 1 ! o $end
$var parameter 3 % s0 $end
$var parameter 3 & s1 $end
$var parameter 3 ' s2 $end
$var parameter 3 ( s3 $end
$var parameter 3 ) s4 $end
$var reg 4 * nstate [3:0] $end
$var reg 4 + state [3:0] $end
$upscope $end
$upscope $end
$enddefinitions $end
$comment Show the parameter values. $end
$dumpall
b100 )
b11 (
b10 '
b1 &
b0 %
$end
#0
$dumpvars
b0 +
b0 *
0$
0#
0"
0!
$end
#5
1"
#10
b1 *
0"
1$
#15
b10 *
b1 +
1"
#20
0"
#25
b10 +
1"
#30
0"
#35
1"
#40
b11 *
0"
0$
#45
b0 *
b11 +
1"
#50
b100 *
0"
1$
#55
1!
b100 +
1"
#60
0"
#65
1"
#70
b1 *
0!
b0 +
0"
1#
#75
1"
#80
0"
#85
1"
#90
0"
0#
#95
b10 *
b1 +
1"
