Verilog/Assignment_1/q2/a2.v
module mycomparator (input a, input b, input c, input d, input e, input f, input g, input h, output y);
    wire n1, n2, n3, n4, w1, w2;

    xnor(n1, a, b);
    xnor(n2, c, d);
    xnor(n3, e, f);
    xnor(n4, g, h);
    and(w1, n1, n2);
    and(w2, n3, w1);
    and(y, n4, w2);

endmodule;

module a2_tb();

	reg A, B, C, D, E, F, G, H;
	wire comp;

	mycomparator G1(A, B, C, D, E, F, G, H, comp);
	
	
	initial begin
        $dumpfile("a2_tb.vcd");
        $dumpvars(0, a2_tb);

        A = 0; B = 0; C = 0; D = 1; E = 0; F = 0; G = 0; H = 0;
        #10; A = 1; B = 0; C = 0; D = 0; E = 0; F = 0; G = 0; H = 0;
        #10; A = 0; B = 1; C = 0; D = 0; E = 0; F = 0; G = 0; H = 0;
        #10; A = 1; B = 1; C = 0; D = 0; E = 0; F = 0; G = 0; H = 0;
        #10; A = 0; B = 0; C = 1; D = 0; E = 0; F = 0; G = 0; H = 0;
        #10; A = 1; B = 0; C = 1; D = 1; E = 0; F = 0; G = 0; H = 0;
        #10; A = 0; B = 1; C = 1; D = 1; E = 0; F = 0; G = 0; H = 0;
        #10; A = 1; B = 1; C = 1; D = 1; E = 0; F = 0; G = 0; H = 0;
        #10;
	end

endmodule;

Verilog/Assignment_1/q2/a2_tb.vcd
$date
	Sun Sep 07 01:28:46 2025
$end
$version
	Icarus Verilog
$end
$timescale
	1s
$end
$scope module a2_tb $end
$var wire 1 ! comp $end
$var reg 1 " A $end
$var reg 1 # B $end
$var reg 1 $ C $end
$var reg 1 % D $end
$var reg 1 & E $end
$var reg 1 ' F $end
$var reg 1 ( G $end
$var reg 1 ) H $end
$scope module G1 $end
$var wire 1 " a $end
$var wire 1 # b $end
$var wire 1 $ c $end
$var wire 1 % d $end
$var wire 1 & e $end
$var wire 1 ' f $end
$var wire 1 ( g $end
$var wire 1 ) h $end
$var wire 1 * n1 $end
$var wire 1 + n2 $end
$var wire 1 , n3 $end
$var wire 1 - n4 $end
$var wire 1 . w1 $end
$var wire 1 / w2 $end
$var wire 1 ! y $end
$upscope $end
$upscope $end
$enddefinitions $end
$comment Show the parameter values. $end
$dumpall
$end
#0
$dumpvars
0/
0.
1-
1,
0+
1*
0)
0(
0'
0&
1%
0$
0#
0"
0!
$end
#10
1+
0*
0%
1"
#20
1#
0"
#30
1!
1/
1.
1*
1"
#40
0!
0/
0.
0+
1$
0#
0"
#50
1+
0*
1%
1"
#60
1#
0"
#70
1!
1/
1.
1*
1"
