Verilog/Assignment_1/q4/a4_decoder.v
module my3inputand (input a, input b, input c, output y);
    wire w;
    and(w, a, b);
    and(y, c, w);
endmodule    

module mydecoder3to8 (input a, input b, input c, output s, output t, output u, output v, output w, output x, output y, output z);
    wire na, nb, nc;
    not(na, a);
    not(nb, b);
    not(nc, c);
    my3inputand and1 (.a(na), .b(nb), .c(nc), .y(s));
    my3inputand and2 (.a(na), .b(nb), .c(c), .y(t));
    my3inputand and3 (.a(na), .b(b), .c(nc), .y(u));
    my3inputand and4 (.a(na), .b(b), .c(c), .y(v));
    my3inputand and5 (.a(a), .b(nb), .c(nc), .y(w));
    my3inputand and6 (.a(a), .b(nb), .c(c), .y(x));
    my3inputand and7 (.a(a), .b(b), .c(nc), .y(y));
    my3inputand and8 (.a(a), .b(b), .c(c), .y(z));
endmodule

module a4_decoder_tb();

	reg A, B, C;
	wire  D, E, F, G, H, I, J, K;

	mydecoder3to8 D1(A, B, C, D, E, F, G, H, I, J, K);
	
	
	initial begin
        $dumpfile("a4_decoder_tb.vcd");
        $dumpvars(0, a4_decoder_tb);

        A = 0; B = 0; C = 0;
        #10; A = 0; B = 0; C = 1;
        #10; A = 0; B = 1; C = 0;
        #10; A = 0; B = 1; C = 1;
        #10; A = 1; B = 0; C = 0;
        #10; A = 1; B = 0; C = 1;
        #10; A = 1; B = 1; C = 0;
        #10; A = 1; B = 1; C = 1;
        #10;
	end

endmodule

Verilog/Assignment_1/q4/a4_decoder_tb.vcd
$date
	Mon Sep 08 17:19:09 2025
$end
$version
	Icarus Verilog
$end
$timescale
	1s
$end
$scope module a4_decoder_tb $end
$var wire 1 ! K $end
$var wire 1 " J $end
$var wire 1 # I $end
$var wire 1 $ H $end
$var wire 1 % G $end
$var wire 1 & F $end
$var wire 1 ' E $end
$var wire 1 ( D $end
$var reg 1 ) A $end
$var reg 1 * B $end
$var reg 1 + C $end
$scope module D1 $end
$var wire 1 ) a $end
$var wire 1 * b $end
$var wire 1 + c $end
$var wire 1 , na $end
$var wire 1 - nb $end
$var wire 1 . nc $end
$var wire 1 ! z $end
$var wire 1 " y $end
$var wire 1 # x $end
$var wire 1 $ w $end
$var wire 1 % v $end
$var wire 1 & u $end
$var wire 1 ' t $end
$var wire 1 ( s $end
$scope module and1 $end
$var wire 1 , a $end
$var wire 1 - b $end
$var wire 1 . c $end
$var wire 1 / w $end
$var wire 1 ( y $end
$upscope $end
$scope module and2 $end
$var wire 1 , a $end
$var wire 1 - b $end
$var wire 1 + c $end
$var wire 1 0 w $end
$var wire 1 ' y $end
$upscope $end
$scope module and3 $end
$var wire 1 , a $end
$var wire 1 * b $end
$var wire 1 . c $end
$var wire 1 1 w $end
$var wire 1 & y $end
$upscope $end
$scope module and4 $end
$var wire 1 , a $end
$var wire 1 * b $end
$var wire 1 + c $end
$var wire 1 2 w $end
$var wire 1 % y $end
$upscope $end
$scope module and5 $end
$var wire 1 ) a $end
$var wire 1 - b $end
$var wire 1 . c $end
$var wire 1 3 w $end
$var wire 1 $ y $end
$upscope $end
$scope module and6 $end
$var wire 1 ) a $end
$var wire 1 - b $end
$var wire 1 + c $end
$var wire 1 4 w $end
$var wire 1 # y $end
$upscope $end
$scope module and7 $end
$var wire 1 ) a $end
$var wire 1 * b $end
$var wire 1 . c $end
$var wire 1 5 w $end
$var wire 1 " y $end
$upscope $end
$scope module and8 $end
$var wire 1 ) a $end
$var wire 1 * b $end
$var wire 1 + c $end
$var wire 1 6 w $end
$var wire 1 ! y $end
$upscope $end
$upscope $end
$upscope $end
$enddefinitions $end
$comment Show the parameter values. $end
$dumpall
$end
#0
$dumpvars
06
05
04
03
02
01
10
1/
1.
1-
1,
0+
0*
0)
1(
0'
0&
0%
0$
0#
0"
0!
$end
#10
0(
0.
1'
1+
#20
0/
00
1&
1.
0'
0-
11
12
0+
1*
#30
0&
0.
1%
1+
#40
1$
13
14
1.
0%
1-
01
02
0,
0+
0*
1)
#50
0$
0.
1#
1+
#60
03
04
1"
1.
0#
0-
15
16
0+
1*
#70
0"
0.
1!
1+
