Verilog/Assignment_1/q4/a4_mux.v
module mymux2to1 (input a, input b, input s, output y);
    wire w1, w2, ns;
    not(ns, s);
    and(w1, a, ns);
    and(w2, b, s);
    or(y, w1, w2);
endmodule

module mymux4to1 (input a, input b, input c, input d, input s, input t, output y);
    wire w3, w4;
    mymux2to1 M1 (.a(a), .b(b), .s(t), .y(w3));
    mymux2to1 M2 (.a(c), .b(d), .s(t), .y(w4));
    mymux2to1 M3 (.a(w3), .b(w4), .s(s), .y(y));
endmodule
     
module a4_mux_tb();

	reg A, B, C, D, E, F;
	wire Y;

	mymux4to1 G1(A, B, C, D, E, F, Y);
	
	
	initial begin
        $dumpfile("a4_mux_tb.vcd");
        $dumpvars(0, a4_mux_tb);

        A = 0; B = 0; C = 0; D = 1; E = 0; F = 0;
        #10; A = 1; B = 0; C = 0; D = 0; E = 0; F = 0;
        #10; A = 0; B = 1; C = 0; D = 0; E = 0; F = 0;
        #10; A = 1; B = 1; C = 0; D = 0; E = 0; F = 1;
        #10; A = 0; B = 0; C = 1; D = 0; E = 0; F = 0;
        #10; A = 1; B = 0; C = 1; D = 1; E = 1; F = 0;
        #10; A = 0; B = 1; C = 1; D = 1; E = 0; F = 0;
        #10; A = 1; B = 1; C = 1; D = 1; E = 1; F = 1;
        #10;
	end

endmodule;

Verilog/Assignment_1/q4/a4_mux_tb.vcd
$date
	Mon Sep 08 17:21:49 2025
$end
$version
	Icarus Verilog
$end
$timescale
	1s
$end
$scope module a4_mux_tb $end
$var wire 1 ! Y $end
$var reg 1 " A $end
$var reg 1 # B $end
$var reg 1 $ C $end
$var reg 1 % D $end
$var reg 1 & E $end
$var reg 1 ' F $end
$scope module G1 $end
$var wire 1 " a $end
$var wire 1 # b $end
$var wire 1 $ c $end
$var wire 1 % d $end
$var wire 1 & s $end
$var wire 1 ' t $end
$var wire 1 ! y $end
$var wire 1 ( w4 $end
$var wire 1 ) w3 $end
$scope module M1 $end
$var wire 1 " a $end
$var wire 1 # b $end
$var wire 1 * ns $end
$var wire 1 ' s $end
$var wire 1 + w1 $end
$var wire 1 , w2 $end
$var wire 1 ) y $end
$upscope $end
$scope module M2 $end
$var wire 1 $ a $end
$var wire 1 % b $end
$var wire 1 - ns $end
$var wire 1 ' s $end
$var wire 1 . w1 $end
$var wire 1 / w2 $end
$var wire 1 ( y $end
$upscope $end
$scope module M3 $end
$var wire 1 ) a $end
$var wire 1 ( b $end
$var wire 1 0 ns $end
$var wire 1 & s $end
$var wire 1 1 w1 $end
$var wire 1 2 w2 $end
$var wire 1 ! y $end
$upscope $end
$upscope $end
$upscope $end
$enddefinitions $end
$comment Show the parameter values. $end
$dumpall
$end
#0
$dumpvars
02
01
10
0/
0.
1-
0,
0+
1*
0)
0(
0'
0&
1%
0$
0#
0"
0!
$end
#10
1!
11
1)
1+
0%
1"
#20
0!
01
0)
0+
1#
0"
#30
1!
11
1)
0*
1,
0-
0+
1'
1"
#40
0!
1(
01
1.
0)
1*
1-
0,
0'
1$
0#
0"
#50
1!
1)
00
12
1+
1&
1%
1"
#60
0!
0)
10
02
0+
0&
1#
0"
#70
0.
1!
1)
0*
1,
0-
1/
00
12
0+
1'
1&
1"
