Verilog/Assignment_4/q1/a1.v
module mymooreFSM (input reset, input a, b, clk, output o);
    reg [1:0] state, nstate;

    parameter s0 = 2'b00;
    parameter s1 = 2'b01;
    parameter s2 = 2'b10;

    // FSM logic
    always @(posedge clk, posedge reset)
        if (reset) state <= s0;
        else state <= nstate;


    // next state logic (nstate)
    always @(*)
        begin 
            case(state)
                s0: nstate = a ? s1 : s0;
                s1: nstate = b ? s2 : s0;
                default: nstate = s0;
            endcase
        end

    assign o = (state == s2);
endmodule

module a1_tb();
    reg reset, a, b, clk;
    wire o;

    mymooreFSM Moore (reset, a, b, clk, o);

    initial clk = 0;
    always begin
        #5;
        clk = ~clk;
    end

    initial begin
        $dumpfile("a1_tb.vcd");
        $dumpvars(0,a1_tb);

        // S0
        reset = 0; a = 1; b = 0; #10;  // S1
        reset = 0; a = 1; b = 1; #10;  // S2
        reset = 1; a = 0; b = 0; #10;  // S0
        reset = 0; a = 1; b = 0; #10;  // S1
        reset = 0; a = 1; b = 1; #10;  // S2
        reset = 0; a = 0; b = 0; #10;  // S0
        $finish;
    end


endmodule

Verilog/Assignment_4/q1/a1_tb.vcd
$date
	Thu Sep 18 22:21:20 2025
$end
$version
	Icarus Verilog
$end
$timescale
	1s
$end
$scope module a1_tb $end
$var wire 1 ! o $end
$var reg 1 " a $end
$var reg 1 # b $end
$var reg 1 $ clk $end
$var reg 1 % reset $end
$scope module Moore $end
$var wire 1 " a $end
$var wire 1 # b $end
$var wire 1 $ clk $end
$var wire 1 % reset $end
$var wire 1 ! o $end
$var parameter 2 & s0 $end
$var parameter 2 ' s1 $end
$var parameter 2 ( s2 $end
$var reg 2 ) nstate [1:0] $end
$var reg 2 * state [1:0] $end
$upscope $end
$upscope $end
$enddefinitions $end
$comment Show the parameter values. $end
$dumpall
b10 (
b1 '
b0 &
$end
#0
$dumpvars
bx *
b0 )
0%
0$
0#
1"
x!
$end
#5
b1 )
0!
b0 *
1$
#10
0$
1#
#15
b10 )
b1 *
1$
#20
b0 *
b0 )
0$
0#
0"
1%
#25
1$
#30
b1 )
0$
1"
0%
#35
b0 )
b1 *
1$
#40
b10 )
0$
1#
#45
b0 )
1!
b10 *
1$
#50
0$
0#
0"
#55
0!
b0 *
1$
