Verilog/Assignment_3/q4/a4.v
module grayupcounter (input up, input clk, output reg [2:0] q);
    initial q = 3'b000;
    always @(posedge clk)
        begin
            if (up)
                begin
                    q[2] <= q[0] ? q[2] : q[1];
                    q[1] <= q[0] ? ~q[2] : q[1];
                    q[0] <= ~(q[2] ^ q[1]);
                end
        end
endmodule

module a4_tb();
    reg up;
    reg clk;
    wire [2:0] q;

    grayupcounter GUC (.clk(clk), .up(up), .q(q));

    initial clk = 0;
    always begin
        #5;
        clk = ~clk;
    end

    initial begin
        $dumpfile("a4_tb.vcd");
        $dumpvars(0,a4_tb);

        up = 1; #37;
        up = 0; #10;
        up = 1; #33;

        $finish;
    end
endmodule

Verilog/Assignment_3/q4/a4_tb.vcd
$date
	Fri Sep 19 08:43:41 2025
$end
$version
	Icarus Verilog
$end
$timescale
	1s
$end
$scope module a4_tb $end
$var wire 3 ! q [2:0] $end
$var reg 1 " clk $end
$var reg 1 # up $end
$scope module GUC $end
$var wire 1 " clk $end
$var wire 1 # up $end
$var reg 3 $ q [2:0] $end
$upscope $end
$upscope $end
$enddefinitions $end
$comment Show the parameter values. $end
$dumpall
$end
#0
$dumpvars
b0 $
1#
0"
b0 !
$end
#5
b1 !
b1 $
1"
#10
0"
#15
b11 !
b11 $
1"
#20
0"
#25
b10 !
b10 $
1"
#30
0"
#35
b110 !
b110 $
1"
#37
0#
#40
0"
#45
1"
#47
1#
#50
0"
#55
b111 !
b111 $
1"
#60
0"
#65
b101 !
b101 $
1"
#70
0"
#75
b100 !
b100 $
1"
